m3u8_To_MP4/__init__.py
m3u8_To_MP4/async_processor.py
m3u8_To_MP4/multithreads_processor.py
m3u8_To_MP4/sync_processor.py
m3u8_To_MP4/v2_abstract_crawler_processor.py
m3u8_To_MP4/v2_abstract_processor.py
m3u8_To_MP4/v2_abstract_task_processor.py
m3u8_To_MP4/v2_async_processor.py
m3u8_To_MP4/v2_multithreads_processor.py
m3u8_To_MP4/helpers/__init__.py
m3u8_To_MP4/helpers/path_helper.py
m3u8_To_MP4/helpers/printer_helper.py
m3u8_To_MP4/networks/__init__.py
m3u8_To_MP4/networks/http_base.py
m3u8_To_MP4/networks/asynchronous/__init__.py
m3u8_To_MP4/networks/asynchronous/async_DNS.py
m3u8_To_MP4/networks/asynchronous/async_http.py
m3u8_To_MP4/networks/asynchronous/async_producer_consumer.py
m3u8_To_MP4/networks/synchronous/__init__.py
m3u8_To_MP4/networks/synchronous/sync_DNS.py
m3u8_To_MP4/networks/synchronous/sync_http.py
m3u8_To_MP4/networks/synchronous/sync_http_requester.py
m3u8_To_MP4-0.1.10.dist-info/LICENSE
m3u8_To_MP4-0.1.10.dist-info/METADATA
m3u8_To_MP4-0.1.10.dist-info/WHEEL
m3u8_To_MP4-0.1.10.dist-info/top_level.txt
m3u8_To_MP4-0.1.10.dist-info/RECORD
