Metadata-Version: 2.1
Name: m3u8-To-MP4
Version: 0.1.10
Summary: Python downloader for saving m3u8 video to local MP4 file.
Home-page: https://github.com/songs18/m3u8_To_MP4
Author: songs18
Author-email: songhaohao2018@cqu.edu.cn
License: MIT
Platform: all
Requires-Python: >=3.7
License-File: LICENSE
Requires-Dist: iso8601 (>=0.1.14)
Requires-Dist: m3u8 (>=0.9.0)
Requires-Dist: pycryptodome (>=3.10.1)
